MANIFEST.in
requirements.txt
setup.py
due_deligence/__init__.py
due_deligence/__main__.py
due_deligence/cli.py
due_deligence/due_deligence.py
due_deligence.egg-info/PKG-INFO
due_deligence.egg-info/SOURCES.txt
due_deligence.egg-info/dependency_links.txt
due_deligence.egg-info/entry_points.txt
due_deligence.egg-info/requires.txt
due_deligence.egg-info/top_level.txt
due_deligence/adapter/__init__.py
due_deligence/adapter/deligence.py
due_deligence/adapter/document.py
due_deligence/adapter/stock.py
due_deligence/adapter/http/__init__.py
due_deligence/adapter/http/cache_requests.py
due_deligence/adapter/http/requests.py
due_deligence/adapter/http/xbrl_obj_downloader.py
due_deligence/adapter/presenter/__init__.py
due_deligence/adapter/presenter/cli_progress_presenter.py
due_deligence/adapter/presenter/null_progress_presenter.py
due_deligence/adapter/presenter/result_json_presenter.py
due_deligence/adapter/presenter/result_screen_presenter.py
due_deligence/adapter/presenter/result_today_recommend_presenter.py
due_deligence/controller/__init__.py
due_deligence/controller/dd_controller.py
due_deligence/domain_model/__init__.py
due_deligence/domain_model/deligence.py
due_deligence/domain_model/document.py
due_deligence/domain_model/stock.py
due_deligence/filtering/__init__.py
due_deligence/filtering/result_capital_ratio_filter.py
due_deligence/filtering/result_filter.py
due_deligence/filtering/result_stock_price_filter.py
due_deligence/filtering/result_underpriced_filter.py
due_deligence/myconfig/__init__.py
due_deligence/myconfig/inject_config.py
due_deligence/myconfig/myconfig.py
due_deligence/util/__init__.py
due_deligence/util/progress_presenter.py