Metadata-Version: 1.0
Name: due-deligence
Version: 1.42
Summary: EDINETから有価証券報告書を取得して企業の割安度を判定します。
Home-page: https://github.com/koboriakira/due_deligence
Author: Kobori Akira
Author-email: private.beats@gmail.com
License: MIT
Platform: UNKNOWN
